dash_flexlayout/FlexLayout.py
dash_flexlayout/Tab.py
dash_flexlayout/__init__.py
dash_flexlayout/_imports_.py
dash_flexlayout/dash_flexlayout.js
dash_flexlayout/metadata.json
dash_flexlayout/package-info.json
dash_flexlayout-0.0.1.dist-info/LICENSE
dash_flexlayout-0.0.1.dist-info/METADATA
dash_flexlayout-0.0.1.dist-info/WHEEL
dash_flexlayout-0.0.1.dist-info/top_level.txt
dash_flexlayout-0.0.1.dist-info/RECORD
