Metadata-Version: 2.1
Name: dash-flexlayout
Version: 0.0.1
Summary: Project Description
Author: Ben Weise <ben.weise@gmail.com>
Classifier: Framework :: Dash
License-File: LICENSE
